msplotly/__init__.py
msplotly/app.py
msplotly/arrow.py
msplotly/cli.py
msplotly/gb_files_manipulation.py
msplotly/miscellaneous.py
msplotly/plotter.py
msplotly/rectangle_bezier.py
msplotly/assets/__init__.py
msplotly/assets/shutdown.js
msplotly/assets/style.css
msplotly/images/MSPlotly_app.png
msplotly/images/__init__.py
msplotly/images/logo.png
msplotly-0.0.18.dist-info/LICENSE
msplotly-0.0.18.dist-info/METADATA
msplotly-0.0.18.dist-info/WHEEL
msplotly-0.0.18.dist-info/entry_points.txt
msplotly-0.0.18.dist-info/top_level.txt
msplotly-0.0.18.dist-info/RECORD
