Metadata-Version: 2.1
Name: msplotly
Version: 0.0.18
Summary: Make graphical representations of BLASTn alignments
Author-email: Ivan Munoz-Gutierrez <ivan.munoz.gutierrez@gmail.com>
Maintainer-email: Ivan Munoz-Gutierrez <ivan.munoz.gutierrez@gmail.com>
License: BSD 3-Clause License
Project-URL: Repository, https://github.com/ivanmugu/msplotly.git
Keywords: DNA alignments,BLASTn,Graphical BLASTn alignments,easyfig
Classifier: Programming Language :: Python
Classifier: License :: OSI Approved :: BSD License
Classifier: Intended Audience :: Science/Research
Classifier: Operating System :: OS Independent
Classifier: Topic :: Scientific/Engineering :: Bio-Informatics
Requires-Python: >=3.11
License-File: LICENSE
Requires-Dist: bezier
Requires-Dist: biopython
Requires-Dist: dash
Requires-Dist: dash_ag_grid
Requires-Dist: dash-bootstrap-components
Requires-Dist: dash-iconify
Requires-Dist: dash-mantine_components
Requires-Dist: kaleido
Requires-Dist: matplotlib
Requires-Dist: plotly
Requires-Dist: pandas
